fast_rpc/__init__.py
fast_rpc/protocol/__init__.py
fast_rpc/serialization/__init__.py
fast_rpc/serialization/constants.py
fast_rpc/serialization/decoders.py
fast_rpc/serialization/encoders.py
fast_rpc/serialization/types.py
fast_rpc-0.1.0.dist-info/LICENSE
fast_rpc-0.1.0.dist-info/WHEEL
fast_rpc-0.1.0.dist-info/METADATA
fast_rpc-0.1.0.dist-info/RECORD
